robust_mixed_dist/__init__.py
robust_mixed_dist/binary.py
robust_mixed_dist/mixed.py
robust_mixed_dist/multiclass.py
robust_mixed_dist/quantitative.py
robust_mixed_dist-0.1.9.dist-info/licenses/LICENSE
robust_mixed_dist-0.1.9.dist-info/METADATA
robust_mixed_dist-0.1.9.dist-info/WHEEL
robust_mixed_dist-0.1.9.dist-info/top_level.txt
robust_mixed_dist-0.1.9.dist-info/RECORD
