Metadata-Version: 2.4
Name: robust-mixed-dist
Version: 0.1.9
Summary: Compute statistical robust distances for mixed data.
Home-page: https://github.com/FabioScielzoOrtiz/robust_mixed_dist-package
Author: Fabio Scielzo Ortiz
Author-email: fabio.scielzoortiz@gmail.com
Classifier: Programming Language :: Python :: 3
Classifier: License :: OSI Approved :: MIT License
Classifier: Operating System :: OS Independent
Requires-Python: >=3.7
License-File: LICENSE
Requires-Dist: polars
Requires-Dist: numpy
Requires-Dist: pandas
Requires-Dist: scipy
Dynamic: author
Dynamic: author-email
Dynamic: classifier
Dynamic: description
Dynamic: description-content-type
Dynamic: home-page
Dynamic: license-file
Dynamic: requires-dist
Dynamic: requires-python
Dynamic: summary
